{
  "tool": "glm_stream",
  "label": "paragraph_bullets",
  "timestamp": "2025-09-28T09:46:08.115882+00:00",
  "request": {
    "prompt": "Write a short paragraph about advantages of streaming responses in UIs, then list 3 bullet points.",
    "use_websearch": false
  },
  "outputs": [
    {
      "type": "text",
      "text": "{\"status\": \"continuation_available\", \"content\": \"=== PROGRESS ===\\n[PROGRESS] chat: Starting execution\\n[PROGRESS] chat: Request validated\\n[PROGRESS] chat: Model/context ready: glm-4.5-flash\\n[PROGRESS] chat: Generating response (~1,492 tokens)\\n=== END PROGRESS ===\\n\\nStreaming responses in UIs provide a significantly improved user experience by delivering content incrementally rather than waiting for the complete response to be processed. This approach reduces perceived latency, keeps users engaged with real-time feedback, and allows them to start interacting with content as soon as it becomes available, rather than facing frustrating blank screens or loading indicators.\\n\\nKey advantages include:\\n• Improved perceived performance: Users receive content immediately, making the application feel faster and more responsive even if the backend processing time remains the same\\n• Enhanced user engagement: The continuous flow of information maintains user attention and provides visual feedback that processing is actively happening\\n• Better resource utilization: Users can start interacting with partial results or begin consuming content while the system continues processing remaining data, optimizing overall workflow efficiency\\n\\n---\\n\\nAGENT'S TURN: Evaluate this perspective alongside your analysis to form a comprehensive solution and continue with the user's request and task at hand.\", \"content_type\": \"text\", \"metadata\": {\"tool_name\": \"chat\", \"conversation_ready\": true, \"model_used\": \"glm-4.5-flash\", \"provider_used\": \"glm\", \"progress\": [\"chat: Starting execution\", \"chat: Request validated\", \"chat: Model/context ready: glm-4.5-flash\", \"chat: Generating response (~1,492 tokens)\"]}, \"continuation_offer\": {\"continuation_id\": \"e8735bdf-665c-4218-a0b1-21a516b8eb4e\", \"note\": \"Claude can continue this conversation for 19 more exchanges.\", \"remaining_turns\": 19}}"
    },
    {
      "type": "text",
      "text": "=== MCP CALL SUMMARY ===\nTool: chat | Status: COMPLETE (Step 1/? complete)\nDuration: 9.9s | Model: glm-4.5-flash | Tokens: ~471\nContinuation ID: -\nNext Action Required: None\nExpert Validation: Disabled\n=== END SUMMARY ===\n\n=== PROGRESS ===\n[PROGRESS] chat: Starting execution\n[PROGRESS] chat: Request validated\n[PROGRESS] chat: Model/context ready: glm-4.5-flash\n[PROGRESS] chat: Generating response (~1,492 tokens)\n=== END PROGRESS ===\nreq_id=d2a9c378-6319-42b0-b503-390c7bb2b7fa\n\n<details><summary>Tool activity (req_id=d2a9c378-6319-42b0-b503-390c7bb2b7fa)</summary>\n\n=== PROGRESS ===\n[PROGRESS] chat: Starting execution\n[PROGRESS] chat: Request validated\n[PROGRESS] chat: Model/context ready: glm-4.5-flash\n[PROGRESS] chat: Generating response (~1,492 tokens)\n=== END PROGRESS ===\n</details>"
    }
  ]
}