{
  "tool": "glm_stream",
  "label": "paragraph_bullets",
  "timestamp": "2025-09-28T10:02:01.467807+00:00",
  "request": {
    "prompt": "Write a short paragraph about advantages of streaming responses in UIs, then list 3 bullet points.",
    "use_websearch": false
  },
  "outputs": [
    {
      "type": "text",
      "text": "{\"status\": \"continuation_available\", \"content\": \"=== PROGRESS ===\\n[PROGRESS] chat: Starting execution\\n[PROGRESS] chat: Request validated\\n[PROGRESS] chat: Model/context ready: glm-4.5-flash\\n[PROGRESS] chat: Generating response (~1,492 tokens)\\n=== END PROGRESS ===\\n\\nStreaming responses in UIs provide a significantly improved user experience by delivering content incrementally rather than waiting for the complete response to load. This approach reduces perceived latency, makes applications feel more responsive, and allows users to start consuming information immediately while the rest continues to load in the background.\\n\\nKey advantages include:\\n• Improved perceived performance and reduced user frustration through immediate visual feedback\\n• Better resource utilization as the browser can render content progressively rather than waiting for the complete payload\\n• Enhanced user engagement with content that becomes available immediately, creating a more natural and responsive interaction flow\\n\\n---\\n\\nAGENT'S TURN: Evaluate this perspective alongside your analysis to form a comprehensive solution and continue with the user's request and task at hand.\", \"content_type\": \"text\", \"metadata\": {\"tool_name\": \"chat\", \"conversation_ready\": true, \"model_used\": \"glm-4.5-flash\", \"provider_used\": \"glm\", \"progress\": [\"chat: Starting execution\", \"chat: Request validated\", \"chat: Model/context ready: glm-4.5-flash\", \"chat: Generating response (~1,492 tokens)\"]}, \"continuation_offer\": {\"continuation_id\": \"84add245-d008-452e-8dc9-492c74add602\", \"note\": \"Claude can continue this conversation for 19 more exchanges.\", \"remaining_turns\": 19}}"
    },
    {
      "type": "text",
      "text": "=== MCP CALL SUMMARY ===\nTool: chat | Status: COMPLETE (Step 1/? complete)\nDuration: 10.0s | Model: glm-4.5-flash | Tokens: ~413\nContinuation ID: -\nNext Action Required: None\nExpert Validation: Disabled\n=== END SUMMARY ===\n\n=== PROGRESS ===\n[PROGRESS] chat: Starting execution\n[PROGRESS] chat: Request validated\n[PROGRESS] chat: Model/context ready: glm-4.5-flash\n[PROGRESS] chat: Generating response (~1,492 tokens)\n=== END PROGRESS ===\nreq_id=fc83c6cc-e33b-4bc6-ba6d-14638cb94b8e\n\n<details><summary>Tool activity (req_id=fc83c6cc-e33b-4bc6-ba6d-14638cb94b8e)</summary>\n\n=== PROGRESS ===\n[PROGRESS] chat: Starting execution\n[PROGRESS] chat: Request validated\n[PROGRESS] chat: Model/context ready: glm-4.5-flash\n[PROGRESS] chat: Generating response (~1,492 tokens)\n=== END PROGRESS ===\n</details>"
    }
  ]
}