{
  "tool": "glm_stream",
  "label": "paragraph_bullets",
  "timestamp": "2025-09-28T09:26:49.600282+00:00",
  "request": {
    "prompt": "Write a short paragraph about advantages of streaming responses in UIs, then list 3 bullet points.",
    "use_websearch": false
  },
  "outputs": [
    {
      "type": "text",
      "text": "{\"status\": \"continuation_available\", \"content\": \"=== PROGRESS ===\\n[PROGRESS] chat: Starting execution\\n[PROGRESS] chat: Request validated\\n[PROGRESS] chat: Model/context ready: glm-4.5-flash\\n[PROGRESS] chat: Generating response (~1,492 tokens)\\n=== END PROGRESS ===\\n\\nStreaming responses in UIs provide significant advantages over traditional full-response rendering. They improve perceived performance by showing partial content as soon as it becomes available, reducing the user's perception of wait time. This approach creates a more engaging and responsive experience, as users can begin consuming or interacting with content before it's fully loaded. Streaming also enables better handling of large responses by breaking them into manageable chunks, reducing memory overhead and improving application stability.\\n\\n• Enhanced user experience through progressive rendering and reduced perceived latency\\n• Improved resource efficiency by processing and displaying content in smaller, manageable chunks\\n• Better error handling and recovery capabilities with partial content delivery\\n\\n---\\n\\nAGENT'S TURN: Evaluate this perspective alongside your analysis to form a comprehensive solution and continue with the user's request and task at hand.\", \"content_type\": \"text\", \"metadata\": {\"tool_name\": \"chat\", \"conversation_ready\": true, \"model_used\": \"glm-4.5-flash\", \"provider_used\": \"glm\", \"progress\": [\"chat: Starting execution\", \"chat: Request validated\", \"chat: Model/context ready: glm-4.5-flash\", \"chat: Generating response (~1,492 tokens)\"]}, \"continuation_offer\": {\"continuation_id\": \"39835bce-8033-43a2-87e3-b141b866a869\", \"note\": \"Claude can continue this conversation for 19 more exchanges.\", \"remaining_turns\": 19}}"
    },
    {
      "type": "text",
      "text": "=== MCP CALL SUMMARY ===\nTool: chat | Status: COMPLETE (Step 1/? complete)\nDuration: 13.2s | Model: glm-4.5-flash | Tokens: ~432\nContinuation ID: -\nNext Action Required: None\nExpert Validation: Disabled\n=== END SUMMARY ===\n\n=== PROGRESS ===\n[PROGRESS] chat: Starting execution\n[PROGRESS] chat: Request validated\n[PROGRESS] chat: Model/context ready: glm-4.5-flash\n[PROGRESS] chat: Generating response (~1,492 tokens)\n=== END PROGRESS ===\nreq_id=d434b31f-087c-4a5c-a4db-520d013cdc44\n\n<details><summary>Tool activity (req_id=d434b31f-087c-4a5c-a4db-520d013cdc44)</summary>\n\n=== PROGRESS ===\n[PROGRESS] chat: Starting execution\n[PROGRESS] chat: Request validated\n[PROGRESS] chat: Model/context ready: glm-4.5-flash\n[PROGRESS] chat: Generating response (~1,492 tokens)\n=== END PROGRESS ===\n</details>"
    }
  ]
}