{
  "tool": "glm_stream",
  "label": "paragraph_bullets",
  "timestamp": "2025-09-28T10:15:05.792673+00:00",
  "request": {
    "prompt": "Write a short paragraph about advantages of streaming responses in UIs, then list 3 bullet points.",
    "use_websearch": false
  },
  "outputs": [
    {
      "type": "text",
      "text": "{\"status\": \"continuation_available\", \"content\": \"=== PROGRESS ===\\n[PROGRESS] chat: Starting execution\\n[PROGRESS] chat: Request validated\\n[PROGRESS] chat: Model/context ready: glm-4.5-flash\\n[PROGRESS] chat: Generating response (~1,492 tokens)\\n=== END PROGRESS ===\\n\\nStreaming responses in UIs provide significant advantages by delivering content progressively rather than waiting for the complete response to load. This approach enhances user experience by reducing perceived wait times, improves performance by allowing the UI to render content as it arrives, and enables users to start interacting with information immediately rather than facing frustrating loading screens. Streaming is particularly valuable for data-heavy applications, real-time updates, and scenarios where content appears incrementally.\\n\\n• Improved perceived performance and reduced user frustration through immediate visual feedback\\n• Enhanced resource utilization as the browser can render content incrementally rather than processing a complete response at once\\n• Better user engagement allowing interaction with content as soon as it becomes available rather than waiting for full load completion\\n\\n---\\n\\nAGENT'S TURN: Evaluate this perspective alongside your analysis to form a comprehensive solution and continue with the user's request and task at hand.\", \"content_type\": \"text\", \"metadata\": {\"tool_name\": \"chat\", \"conversation_ready\": true, \"model_used\": \"glm-4.5-flash\", \"provider_used\": \"glm\", \"progress\": [\"chat: Starting execution\", \"chat: Request validated\", \"chat: Model/context ready: glm-4.5-flash\", \"chat: Generating response (~1,492 tokens)\"]}, \"continuation_offer\": {\"continuation_id\": \"6784fa1b-04bc-4550-be7d-5c28e237fd64\", \"note\": \"Claude can continue this conversation for 19 more exchanges.\", \"remaining_turns\": 19}}"
    },
    {
      "type": "text",
      "text": "=== MCP CALL SUMMARY ===\nTool: chat | Status: COMPLETE (Step 1/? complete)\nDuration: 18.4s | Model: glm-4.5-flash | Tokens: ~456\nContinuation ID: -\nNext Action Required: None\nExpert Validation: Disabled\n=== END SUMMARY ===\n\n=== PROGRESS ===\n[PROGRESS] chat: Starting execution\n[PROGRESS] chat: Request validated\n[PROGRESS] chat: Model/context ready: glm-4.5-flash\n[PROGRESS] chat: Generating response (~1,492 tokens)\n=== END PROGRESS ===\nreq_id=fc9345ae-990e-4243-a6f0-4e39a76ea27b\n\n<details><summary>Tool activity (req_id=fc9345ae-990e-4243-a6f0-4e39a76ea27b)</summary>\n\n=== PROGRESS ===\n[PROGRESS] chat: Starting execution\n[PROGRESS] chat: Request validated\n[PROGRESS] chat: Model/context ready: glm-4.5-flash\n[PROGRESS] chat: Generating response (~1,492 tokens)\n=== END PROGRESS ===\n</details>"
    }
  ]
}