{
  "tool": "glm_stream",
  "label": "paragraph_bullets",
  "timestamp": "2025-09-28T23:50:24.873679+00:00",
  "request": {
    "prompt": "Write a short paragraph about advantages of streaming responses in UIs, then list 3 bullet points.",
    "use_websearch": false
  },
  "outputs": [
    {
      "type": "text",
      "text": "{\"status\": \"continuation_available\", \"content\": \"=== PROGRESS ===\\n[PROGRESS] chat: Starting execution\\n[PROGRESS] chat: Request validated\\n[PROGRESS] chat: Model/context ready: glm-4.5-flash\\n[PROGRESS] chat: Generating response (~1,656 tokens)\\n=== END PROGRESS ===\\n\\nStreaming responses in UIs significantly enhance user experience by providing immediate feedback and reducing perceived loading times. Instead of waiting for the entire response to load before displaying any content, streaming allows progressive rendering of data as it becomes available, creating a more responsive and interactive interface.\\n\\nKey advantages include:\\n- Improved perceived performance: Users start seeing content almost immediately, reducing frustration from waiting for complete responses\\n- Enhanced user experience with progressive rendering: Content appears piece by piece, allowing users to begin interacting with available data while additional content loads\\n- Better error handling and recovery: If an error occurs mid-stream, the system can gracefully handle it without losing all previously loaded content\\n\\n---\\n\\nAGENT'S TURN: Evaluate this perspective alongside your analysis to form a comprehensive solution and continue with the user's request and task at hand.\", \"content_type\": \"text\", \"metadata\": {\"tool_name\": \"chat\", \"conversation_ready\": true, \"model_used\": \"glm-4.5-flash\", \"provider_used\": \"glm\", \"progress\": [\"chat: Starting execution\", \"chat: Request validated\", \"chat: Model/context ready: glm-4.5-flash\", \"chat: Generating response (~1,656 tokens)\"]}, \"continuation_offer\": {\"continuation_id\": \"7996cf62-5989-4dfc-9efe-3f08c603cf5a\", \"note\": \"Claude can continue this conversation for 19 more exchanges.\", \"remaining_turns\": 19}}"
    },
    {
      "type": "text",
      "text": "=== MCP CALL SUMMARY ===\nTool: chat | Status: COMPLETE (Step 1/? complete)\nDuration: 15.6s | Model: glm-4.5-flash | Tokens: ~436\nContinuation ID: -\nNext Action Required: None\nExpert Validation: Disabled\n=== END SUMMARY ===\n\n=== PROGRESS ===\n[PROGRESS] chat: Starting execution\n[PROGRESS] chat: Request validated\n[PROGRESS] chat: Model/context ready: glm-4.5-flash\n[PROGRESS] chat: Generating response (~1,656 tokens)\n=== END PROGRESS ===\nreq_id=a914b26c-ca48-49f3-9cb1-2ba6f4f06efb\n\n<details><summary>Tool activity (req_id=a914b26c-ca48-49f3-9cb1-2ba6f4f06efb)</summary>\n\n=== PROGRESS ===\n[PROGRESS] chat: Starting execution\n[PROGRESS] chat: Request validated\n[PROGRESS] chat: Model/context ready: glm-4.5-flash\n[PROGRESS] chat: Generating response (~1,656 tokens)\n=== END PROGRESS ===\n</details>"
    }
  ]
}