{
  "tool": "glm_stream",
  "label": "paragraph_bullets",
  "timestamp": "2025-09-28T09:32:06.768530+00:00",
  "request": {
    "prompt": "Write a short paragraph about advantages of streaming responses in UIs, then list 3 bullet points.",
    "use_websearch": false
  },
  "outputs": [
    {
      "type": "text",
      "text": "{\"status\": \"continuation_available\", \"content\": \"=== PROGRESS ===\\n[PROGRESS] chat: Starting execution\\n[PROGRESS] chat: Request validated\\n[PROGRESS] chat: Model/context ready: glm-4.5-flash\\n[PROGRESS] chat: Generating response (~1,492 tokens)\\n=== END PROGRESS ===\\n\\n\\nStreaming responses in UIs significantly enhance user experience by providing immediate feedback and reducing perceived wait times. Rather than waiting for the entire response to load before displaying anything, streaming allows content to appear progressively as it becomes available, creating a more fluid and responsive interaction that feels faster and more engaging.\\n\\nKey advantages include:\\n*   Improved perceived performance - Users start consuming content immediately rather than staring at a loading spinner, making the interface feel more responsive even if total processing time remains the same\\n*   Better user engagement - Progressive content display maintains attention and context, reducing the likelihood of users abandoning tasks due to perceived delays\\n*   Enhanced accessibility - Content becomes available incrementally, allowing users with assistive technologies to begin interacting with information sooner rather than waiting for complete responses\\n\\nPlease continue this conversation using the continuation_id from this response if you'd like to explore this further.\\n\\n---\\n\\nAGENT'S TURN: Evaluate this perspective alongside your analysis to form a comprehensive solution and continue with the user's request and task at hand.\", \"content_type\": \"text\", \"metadata\": {\"tool_name\": \"chat\", \"conversation_ready\": true, \"model_used\": \"glm-4.5-flash\", \"provider_used\": \"glm\", \"progress\": [\"chat: Starting execution\", \"chat: Request validated\", \"chat: Model/context ready: glm-4.5-flash\", \"chat: Generating response (~1,492 tokens)\"]}, \"continuation_offer\": {\"continuation_id\": \"90a3fba6-a66d-4882-a795-676dfaa3e43d\", \"note\": \"Claude can continue this conversation for 19 more exchanges.\", \"remaining_turns\": 19}}"
    },
    {
      "type": "text",
      "text": "=== MCP CALL SUMMARY ===\nTool: chat | Status: COMPLETE (Step 1/? complete)\nDuration: 7.1s | Model: glm-4.5-flash | Tokens: ~503\nContinuation ID: -\nNext Action Required: None\nExpert Validation: Disabled\n=== END SUMMARY ===\n\n=== PROGRESS ===\n[PROGRESS] chat: Starting execution\n[PROGRESS] chat: Request validated\n[PROGRESS] chat: Model/context ready: glm-4.5-flash\n[PROGRESS] chat: Generating response (~1,492 tokens)\n=== END PROGRESS ===\nreq_id=623726bb-89e2-4b31-a151-7a863ef5d893\n\n<details><summary>Tool activity (req_id=623726bb-89e2-4b31-a151-7a863ef5d893)</summary>\n\n=== PROGRESS ===\n[PROGRESS] chat: Starting execution\n[PROGRESS] chat: Request validated\n[PROGRESS] chat: Model/context ready: glm-4.5-flash\n[PROGRESS] chat: Generating response (~1,492 tokens)\n=== END PROGRESS ===\n</details>"
    }
  ]
}