{
  "op": "call_tool_res",
  "request_id": "d0b3ea86f83446a980b51485d575e44e",
  "outputs": [
    {
      "type": "text",
      "text": "{\"status\": \"continuation_available\", \"content\": \"=== PROGRESS ===\\n[PROGRESS] chat: Starting execution\\n[PROGRESS] chat: Request validated\\n[PROGRESS] chat: Model/context ready: glm-4.5\\n[PROGRESS] chat: Generating response (~1,962 tokens)\\n=== END PROGRESS ===\\n\\nI'll help you find a recent AI infrastructure news item. To provide you with the most current information, I need to perform a web search first.\\n\\nSEARCH REQUIRED: Please immediately perform a web search on \\\"recent AI infrastructure news 2024\\\" and respond back with the results using the continuation_id from this response. Cannot provide accurate analysis without this current information.\\n\\nOnce I have the search results, I'll provide:\\n- Two concise bullet points summarizing a significant recent development\\n- The URL to the original news source\\n\\nPlease continue this conversation using the continuation_id from this response so I can deliver the requested information.\\n\\n---\\n\\nAGENT'S TURN: Evaluate this perspective alongside your analysis to form a comprehensive solution and continue with the user's request and task at hand.\", \"content_type\": \"text\", \"metadata\": {\"tool_name\": \"chat\", \"conversation_ready\": true, \"model_used\": \"glm-4.5\", \"provider_used\": \"glm\", \"tool_call_events\": [{\"provider\": \"glm\", \"tool_name\": \"chat\", \"args\": {\"model\": \"glm-4.5\", \"use_websearch\": true, \"thinking_mode\": \"medium\"}, \"start_ts\": 1758534645.6496007}], \"progress\": [\"chat: Starting execution\", \"chat: Request validated\", \"chat: Model/context ready: glm-4.5\", \"chat: Generating response (~1,962 tokens)\"]}, \"continuation_offer\": {\"continuation_id\": \"05c0eec7-de20-45de-af7b-7d9dce113f5b\", \"note\": \"Claude can continue this conversation for 19 more exchanges.\", \"remaining_turns\": 19}}"
    },
    {
      "type": "text",
      "text": "=== MCP CALL SUMMARY ===\nTool: chat | Status: COMPLETE (Step 1/? complete)\nDuration: 7.6s | Model: glm-4.5 | Tokens: ~438\nContinuation ID: -\nNext Action Required: None\nExpert Validation: Disabled\n=== END SUMMARY ===\n\n=== PROGRESS ===\n[PROGRESS] chat: Starting execution\n[PROGRESS] chat: Request validated\n[PROGRESS] chat: Model/context ready: glm-4.5\n[PROGRESS] chat: Generating response (~1,962 tokens)\n=== END PROGRESS ===\nreq_id=2278068d-feb9-4172-aee8-754732114727\n\n<details><summary>Tool activity (req_id=2278068d-feb9-4172-aee8-754732114727)</summary>\n\n=== PROGRESS ===\n[PROGRESS] chat: Starting execution\n[PROGRESS] chat: Request validated\n[PROGRESS] chat: Model/context ready: glm-4.5\n[PROGRESS] chat: Generating response (~1,962 tokens)\n=== END PROGRESS ===\n</details>"
    }
  ],
  "text": "{\"status\": \"continuation_available\", \"content\": \"=== PROGRESS ===\\n[PROGRESS] chat: Starting execution\\n[PROGRESS] chat: Request validated\\n[PROGRESS] chat: Model/context ready: glm-4.5\\n[PROGRESS] chat: Generating response (~1,962 tokens)\\n=== END PROGRESS ===\\n\\nI'll help you find a recent AI infrastructure news item. To provide you with the most current information, I need to perform a web search first.\\n\\nSEARCH REQUIRED: Please immediately perform a web search on \\\"recent AI infrastructure news 2024\\\" and respond back with the results using the continuation_id from this response. Cannot provide accurate analysis without this current information.\\n\\nOnce I have the search results, I'll provide:\\n- Two concise bullet points summarizing a significant recent development\\n- The URL to the original news source\\n\\nPlease continue this conversation using the continuation_id from this response so I can deliver the requested information.\\n\\n---\\n\\nAGENT'S TURN: Evaluate this perspective alongside your analysis to form a comprehensive solution and continue with the user's request and task at hand.\", \"content_type\": \"text\", \"metadata\": {\"tool_name\": \"chat\", \"conversation_ready\": true, \"model_used\": \"glm-4.5\", \"provider_used\": \"glm\", \"tool_call_events\": [{\"provider\": \"glm\", \"tool_name\": \"chat\", \"args\": {\"model\": \"glm-4.5\", \"use_websearch\": true, \"thinking_mode\": \"medium\"}, \"start_ts\": 1758534645.6496007}], \"progress\": [\"chat: Starting execution\", \"chat: Request validated\", \"chat: Model/context ready: glm-4.5\", \"chat: Generating response (~1,962 tokens)\"]}, \"continuation_offer\": {\"continuation_id\": \"05c0eec7-de20-45de-af7b-7d9dce113f5b\", \"note\": \"Claude can continue this conversation for 19 more exchanges.\", \"remaining_turns\": 19}}\n\n=== MCP CALL SUMMARY ===\nTool: chat | Status: COMPLETE (Step 1/? complete)\nDuration: 7.6s | Model: glm-4.5 | Tokens: ~438\nContinuation ID: -\nNext Action Required: None\nExpert Validation: Disabled\n=== END SUMMARY ===\n\n=== PROGRESS ===\n[PROGRESS] chat: Starting execution\n[PROGRESS] chat: Request validated\n[PROGRESS] chat: Model/context ready: glm-4.5\n[PROGRESS] chat: Generating response (~1,962 tokens)\n=== END PROGRESS ===\nreq_id=2278068d-feb9-4172-aee8-754732114727\n\n<details><summary>Tool activity (req_id=2278068d-feb9-4172-aee8-754732114727)</summary>\n\n=== PROGRESS ===\n[PROGRESS] chat: Starting execution\n[PROGRESS] chat: Request validated\n[PROGRESS] chat: Model/context ready: glm-4.5\n[PROGRESS] chat: Generating response (~1,962 tokens)\n=== END PROGRESS ===\n</details>"
}